{
  "generatedAt": "2026-07-13T23:08:56.728Z",
  "source": "official-api",
  "officialLatest": {
    "bingo": {
      "game": "bingo",
      "period": "115039383",
      "drawDate": "2026-07-14T07:05:00",
      "redeemableDate": "2026-10-14T00:00:00",
      "numbers": [
        6,
        8,
        14,
        20,
        25,
        29,
        35,
        43,
        44,
        45,
        49,
        56,
        59,
        61,
        67,
        69,
        71,
        72,
        73,
        75
      ],
      "orderNumbers": [
        73,
        75,
        72,
        8,
        61,
        20,
        29,
        43,
        35,
        69,
        67,
        45,
        49,
        56,
        25,
        59,
        71,
        6,
        44,
        14
      ],
      "specialNumber": 14,
      "source": "official-api"
    },
    "daily539": {
      "game": "daily539",
      "period": "115000169",
      "drawDate": "2026-07-13T00:00:00",
      "redeemableDate": "2026-10-13T00:00:00",
      "numbers": [
        3,
        4,
        5,
        34,
        35
      ],
      "source": "official-api"
    },
    "lotto649": {
      "game": "lotto649",
      "period": "115000069",
      "drawDate": "2026-07-10T00:00:00",
      "redeemableDate": "2026-10-12T00:00:00",
      "numbers": [
        3,
        4,
        15,
        18,
        29,
        49
      ],
      "specialNumber": 13,
      "source": "official-api"
    },
    "superLotto638": {
      "game": "superLotto638",
      "period": "115000056",
      "drawDate": "2026-07-13T00:00:00",
      "redeemableDate": "2026-10-13T00:00:00",
      "numbers": [
        11,
        24,
        29,
        32,
        35,
        38
      ],
      "specialNumber": 6,
      "source": "official-api"
    }
  },
  "debugRaw": {
    "bingo": {
      "lotteryBingoLatestPost": {
        "drawTerm": 115039383,
        "dDate": "2026-07-14T07:05:00",
        "eDate": "2026-10-14T00:00:00",
        "bigShowOrder": [
          "06",
          "08",
          "14",
          "20",
          "25",
          "29",
          "35",
          "43",
          "44",
          "45",
          "49",
          "56",
          "59",
          "61",
          "67",
          "69",
          "71",
          "72",
          "73",
          "75"
        ],
        "openShowOrder": [
          "73",
          "75",
          "72",
          "08",
          "61",
          "20",
          "29",
          "43",
          "35",
          "69",
          "67",
          "45",
          "49",
          "56",
          "25",
          "59",
          "71",
          "06",
          "44",
          "14"
        ],
        "prizeNum": {
          "bullEye": "14",
          "highLow": "大",
          "oddEven": "單"
        }
      }
    },
    "bingoWeb": null
  }
}