{
  "generatedAt": "2026-04-09T05:59:56.504Z",
  "source": "official-api",
  "officialLatest": {
    "bingo": {
      "game": "bingo",
      "period": "115019977",
      "drawDate": "2026-04-09T13:55:00",
      "redeemableDate": "2026-07-09T00:00:00",
      "numbers": [
        1,
        4,
        8,
        11,
        22,
        23,
        27,
        33,
        35,
        37,
        40,
        44,
        46,
        47,
        54,
        56,
        63,
        69,
        76,
        79
      ],
      "orderNumbers": [
        11,
        44,
        23,
        69,
        47,
        22,
        56,
        37,
        46,
        4,
        35,
        54,
        1,
        63,
        27,
        33,
        76,
        8,
        79,
        40
      ],
      "specialNumber": 40,
      "source": "official-api"
    },
    "daily539": {
      "game": "daily539",
      "period": "115000087",
      "drawDate": "2026-04-08T00:00:00",
      "redeemableDate": "2026-07-08T00:00:00",
      "numbers": [
        2,
        4,
        5,
        6,
        29
      ],
      "source": "official-api"
    },
    "lotto649": {
      "game": "lotto649",
      "period": "115000042",
      "drawDate": "2026-04-07T00:00:00",
      "redeemableDate": "2026-07-07T00:00:00",
      "numbers": [
        1,
        2,
        6,
        16,
        18,
        26
      ],
      "specialNumber": 47,
      "source": "official-api"
    },
    "superLotto638": {
      "game": "superLotto638",
      "period": "115000028",
      "drawDate": "2026-04-06T00:00:00",
      "redeemableDate": "2026-07-06T00:00:00",
      "numbers": [
        5,
        8,
        22,
        27,
        35,
        38
      ],
      "specialNumber": 4,
      "source": "official-api"
    }
  },
  "debugRaw": {
    "bingo": {
      "lotteryBingoLatestPost": {
        "drawTerm": 115019977,
        "dDate": "2026-04-09T13:55:00",
        "eDate": "2026-07-09T00:00:00",
        "bigShowOrder": [
          "01",
          "04",
          "08",
          "11",
          "22",
          "23",
          "27",
          "33",
          "35",
          "37",
          "40",
          "44",
          "46",
          "47",
          "54",
          "56",
          "63",
          "69",
          "76",
          "79"
        ],
        "openShowOrder": [
          "11",
          "44",
          "23",
          "69",
          "47",
          "22",
          "56",
          "37",
          "46",
          "04",
          "35",
          "54",
          "01",
          "63",
          "27",
          "33",
          "76",
          "08",
          "79",
          "40"
        ],
        "prizeNum": {
          "bullEye": "40",
          "highLow": "－",
          "oddEven": "－"
        }
      }
    },
    "bingoWeb": null
  }
}