{
  "generatedAt": "2026-07-15T03:34:46.557Z",
  "source": "official-api",
  "officialLatest": {
    "bingo": {
      "game": "bingo",
      "period": "115039639",
      "drawDate": "2026-07-15T11:30:00",
      "redeemableDate": "2026-10-15T00:00:00",
      "numbers": [
        2,
        6,
        10,
        11,
        14,
        16,
        22,
        28,
        30,
        35,
        40,
        47,
        49,
        58,
        60,
        63,
        64,
        66,
        68,
        80
      ],
      "orderNumbers": [
        47,
        64,
        63,
        40,
        80,
        60,
        6,
        22,
        16,
        49,
        11,
        68,
        28,
        30,
        58,
        14,
        2,
        35,
        10,
        66
      ],
      "specialNumber": 66,
      "source": "official-api"
    },
    "daily539": {
      "game": "daily539",
      "period": "115000170",
      "drawDate": "2026-07-14T00:00:00",
      "redeemableDate": "2026-10-14T00:00:00",
      "numbers": [
        1,
        6,
        13,
        15,
        37
      ],
      "source": "official-api"
    },
    "lotto649": {
      "game": "lotto649",
      "period": "115000070",
      "drawDate": "2026-07-14T00:00:00",
      "redeemableDate": "2026-10-14T00:00:00",
      "numbers": [
        10,
        25,
        34,
        36,
        45,
        46
      ],
      "specialNumber": 7,
      "source": "official-api"
    },
    "superLotto638": {
      "game": "superLotto638",
      "period": "115000056",
      "drawDate": "2026-07-13T00:00:00",
      "redeemableDate": "2026-10-13T00:00:00",
      "numbers": [
        11,
        24,
        29,
        32,
        35,
        38
      ],
      "specialNumber": 6,
      "source": "official-api"
    }
  },
  "debugRaw": {
    "bingo": {
      "lotteryBingoLatestPost": {
        "drawTerm": 115039639,
        "dDate": "2026-07-15T11:30:00",
        "eDate": "2026-10-15T00:00:00",
        "bigShowOrder": [
          "02",
          "06",
          "10",
          "11",
          "14",
          "16",
          "22",
          "28",
          "30",
          "35",
          "40",
          "47",
          "49",
          "58",
          "60",
          "63",
          "64",
          "66",
          "68",
          "80"
        ],
        "openShowOrder": [
          "47",
          "64",
          "63",
          "40",
          "80",
          "60",
          "06",
          "22",
          "16",
          "49",
          "11",
          "68",
          "28",
          "30",
          "58",
          "14",
          "02",
          "35",
          "10",
          "66"
        ],
        "prizeNum": {
          "bullEye": "66",
          "highLow": "－",
          "oddEven": "雙"
        }
      }
    },
    "bingoWeb": null
  }
}