{
  "generatedAt": "2026-05-17T11:43:07.201Z",
  "source": "official-api",
  "officialLatest": {
    "bingo": {
      "game": "bingo",
      "period": "115027760",
      "drawDate": "2026-05-17T19:40:00",
      "redeemableDate": "2026-08-17T00:00:00",
      "numbers": [
        2,
        8,
        16,
        18,
        28,
        30,
        32,
        35,
        36,
        44,
        46,
        49,
        50,
        51,
        59,
        60,
        61,
        66,
        69,
        74
      ],
      "orderNumbers": [
        2,
        8,
        51,
        60,
        30,
        66,
        49,
        44,
        16,
        74,
        18,
        46,
        50,
        36,
        32,
        28,
        59,
        69,
        61,
        35
      ],
      "specialNumber": 35,
      "source": "official-api"
    },
    "daily539": {
      "game": "daily539",
      "period": "115000120",
      "drawDate": "2026-05-16T00:00:00",
      "redeemableDate": "2026-08-17T00:00:00",
      "numbers": [
        2,
        11,
        28,
        32,
        33
      ],
      "source": "official-api"
    },
    "lotto649": {
      "game": "lotto649",
      "period": "115000053",
      "drawDate": "2026-05-15T00:00:00",
      "redeemableDate": "2026-08-17T00:00:00",
      "numbers": [
        16,
        29,
        30,
        35,
        42,
        43
      ],
      "specialNumber": 1,
      "source": "official-api"
    },
    "superLotto638": {
      "game": "superLotto638",
      "period": "115000039",
      "drawDate": "2026-05-14T00:00:00",
      "redeemableDate": "2026-08-14T00:00:00",
      "numbers": [
        6,
        8,
        9,
        17,
        21,
        29
      ],
      "specialNumber": 8,
      "source": "official-api"
    }
  },
  "debugRaw": {
    "bingo": {
      "lotteryBingoLatestPost": {
        "drawTerm": 115027760,
        "dDate": "2026-05-17T19:40:00",
        "eDate": "2026-08-17T00:00:00",
        "bigShowOrder": [
          "02",
          "08",
          "16",
          "18",
          "28",
          "30",
          "32",
          "35",
          "36",
          "44",
          "46",
          "49",
          "50",
          "51",
          "59",
          "60",
          "61",
          "66",
          "69",
          "74"
        ],
        "openShowOrder": [
          "02",
          "08",
          "51",
          "60",
          "30",
          "66",
          "49",
          "44",
          "16",
          "74",
          "18",
          "46",
          "50",
          "36",
          "32",
          "28",
          "59",
          "69",
          "61",
          "35"
        ],
        "prizeNum": {
          "bullEye": "35",
          "highLow": "－",
          "oddEven": "雙"
        }
      }
    },
    "bingoWeb": null
  }
}