{
  "generatedAt": "2026-07-06T21:53:42.893Z",
  "source": "official-api",
  "officialLatest": {
    "bingo": {
      "game": "bingo",
      "period": "115037961",
      "drawDate": "2026-07-06T23:55:00",
      "redeemableDate": "2026-10-06T00:00:00",
      "numbers": [
        2,
        4,
        7,
        8,
        10,
        12,
        21,
        32,
        33,
        35,
        39,
        43,
        46,
        47,
        48,
        49,
        59,
        60,
        72,
        79
      ],
      "orderNumbers": [
        59,
        4,
        8,
        46,
        48,
        79,
        39,
        43,
        60,
        21,
        72,
        32,
        10,
        35,
        33,
        12,
        7,
        47,
        49,
        2
      ],
      "specialNumber": 2,
      "source": "official-api"
    },
    "daily539": {
      "game": "daily539",
      "period": "115000163",
      "drawDate": "2026-07-06T00:00:00",
      "redeemableDate": "2026-10-06T00:00:00",
      "numbers": [
        1,
        10,
        12,
        14,
        38
      ],
      "source": "official-api"
    },
    "lotto649": {
      "game": "lotto649",
      "period": "115000067",
      "drawDate": "2026-07-03T00:00:00",
      "redeemableDate": "2026-10-05T00:00:00",
      "numbers": [
        11,
        16,
        19,
        23,
        39,
        47
      ],
      "specialNumber": 15,
      "source": "official-api"
    },
    "superLotto638": {
      "game": "superLotto638",
      "period": "115000054",
      "drawDate": "2026-07-06T00:00:00",
      "redeemableDate": "2026-10-06T00:00:00",
      "numbers": [
        4,
        12,
        15,
        24,
        30,
        31
      ],
      "specialNumber": 1,
      "source": "official-api"
    }
  },
  "debugRaw": {
    "bingo": {
      "lotteryBingoLatestPost": {
        "drawTerm": 115037961,
        "dDate": "2026-07-06T23:55:00",
        "eDate": "2026-10-06T00:00:00",
        "bigShowOrder": [
          "02",
          "04",
          "07",
          "08",
          "10",
          "12",
          "21",
          "32",
          "33",
          "35",
          "39",
          "43",
          "46",
          "47",
          "48",
          "49",
          "59",
          "60",
          "72",
          "79"
        ],
        "openShowOrder": [
          "59",
          "04",
          "08",
          "46",
          "48",
          "79",
          "39",
          "43",
          "60",
          "21",
          "72",
          "32",
          "10",
          "35",
          "33",
          "12",
          "07",
          "47",
          "49",
          "02"
        ],
        "prizeNum": {
          "bullEye": "02",
          "highLow": "－",
          "oddEven": "－"
        }
      }
    },
    "bingoWeb": null
  }
}