{
  "generatedAt": "2026-03-22T11:48:22.953Z",
  "source": "official-api",
  "officialLatest": {
    "bingo": {
      "game": "bingo",
      "period": "115016393",
      "drawDate": "2026-03-22T19:45:00",
      "redeemableDate": "2026-06-22T00:00:00",
      "numbers": [
        2,
        9,
        10,
        11,
        16,
        20,
        29,
        33,
        35,
        36,
        39,
        44,
        45,
        59,
        60,
        61,
        66,
        74,
        76,
        78
      ],
      "orderNumbers": [
        60,
        45,
        2,
        11,
        29,
        36,
        16,
        33,
        76,
        78,
        9,
        39,
        35,
        20,
        61,
        74,
        10,
        66,
        59,
        44
      ],
      "specialNumber": 44,
      "source": "official-api"
    },
    "daily539": {
      "game": "daily539",
      "period": "115000072",
      "drawDate": "2026-03-21T00:00:00",
      "redeemableDate": "2026-06-22T00:00:00",
      "numbers": [
        7,
        14,
        15,
        19,
        22
      ],
      "source": "official-api"
    },
    "lotto649": {
      "game": "lotto649",
      "period": "115000037",
      "drawDate": "2026-03-20T00:00:00",
      "redeemableDate": "2026-06-22T00:00:00",
      "numbers": [
        11,
        15,
        33,
        38,
        41,
        43
      ],
      "specialNumber": 21,
      "source": "official-api"
    },
    "superLotto638": {
      "game": "superLotto638",
      "period": "115000023",
      "drawDate": "2026-03-19T00:00:00",
      "redeemableDate": "2026-06-22T00:00:00",
      "numbers": [
        9,
        13,
        14,
        18,
        31,
        34
      ],
      "specialNumber": 1,
      "source": "official-api"
    }
  },
  "debugRaw": {
    "bingo": {
      "lotteryBingoLatestPost": {
        "drawTerm": 115016393,
        "dDate": "2026-03-22T19:45:00",
        "eDate": "2026-06-22T00:00:00",
        "bigShowOrder": [
          "02",
          "09",
          "10",
          "11",
          "16",
          "20",
          "29",
          "33",
          "35",
          "36",
          "39",
          "44",
          "45",
          "59",
          "60",
          "61",
          "66",
          "74",
          "76",
          "78"
        ],
        "openShowOrder": [
          "60",
          "45",
          "02",
          "11",
          "29",
          "36",
          "16",
          "33",
          "76",
          "78",
          "09",
          "39",
          "35",
          "20",
          "61",
          "74",
          "10",
          "66",
          "59",
          "44"
        ],
        "prizeNum": {
          "bullEye": "44",
          "highLow": "－",
          "oddEven": "－"
        }
      }
    },
    "bingoWeb": null
  }
}