{
  "generatedAt": "2026-07-11T12:36:55.473Z",
  "source": "official-api",
  "officialLatest": {
    "bingo": {
      "game": "bingo",
      "period": "115038936",
      "drawDate": "2026-07-11T20:35:00",
      "redeemableDate": "2026-10-12T00:00:00",
      "numbers": [
        4,
        6,
        9,
        12,
        16,
        17,
        19,
        22,
        33,
        34,
        39,
        42,
        43,
        46,
        59,
        63,
        69,
        75,
        76,
        78
      ],
      "orderNumbers": [
        17,
        76,
        34,
        9,
        33,
        78,
        4,
        16,
        46,
        22,
        59,
        43,
        12,
        19,
        42,
        63,
        39,
        69,
        75,
        6
      ],
      "specialNumber": 6,
      "source": "official-api"
    },
    "daily539": {
      "game": "daily539",
      "period": "115000167",
      "drawDate": "2026-07-10T00:00:00",
      "redeemableDate": "2026-10-12T00:00:00",
      "numbers": [
        5,
        13,
        15,
        21,
        26
      ],
      "source": "official-api"
    },
    "lotto649": {
      "game": "lotto649",
      "period": "115000069",
      "drawDate": "2026-07-10T00:00:00",
      "redeemableDate": "2026-10-12T00:00:00",
      "numbers": [
        3,
        4,
        15,
        18,
        29,
        49
      ],
      "specialNumber": 13,
      "source": "official-api"
    },
    "superLotto638": {
      "game": "superLotto638",
      "period": "115000055",
      "drawDate": "2026-07-09T00:00:00",
      "redeemableDate": "2026-10-12T00:00:00",
      "numbers": [
        10,
        22,
        24,
        29,
        35,
        37
      ],
      "specialNumber": 6,
      "source": "official-api"
    }
  },
  "debugRaw": {
    "bingo": {
      "lotteryBingoLatestPost": {
        "drawTerm": 115038936,
        "dDate": "2026-07-11T20:35:00",
        "eDate": "2026-10-12T00:00:00",
        "bigShowOrder": [
          "04",
          "06",
          "09",
          "12",
          "16",
          "17",
          "19",
          "22",
          "33",
          "34",
          "39",
          "42",
          "43",
          "46",
          "59",
          "63",
          "69",
          "75",
          "76",
          "78"
        ],
        "openShowOrder": [
          "17",
          "76",
          "34",
          "09",
          "33",
          "78",
          "04",
          "16",
          "46",
          "22",
          "59",
          "43",
          "12",
          "19",
          "42",
          "63",
          "39",
          "69",
          "75",
          "06"
        ],
        "prizeNum": {
          "bullEye": "06",
          "highLow": "－",
          "oddEven": "－"
        }
      }
    },
    "bingoWeb": null
  }
}