{
  "generatedAt": "2026-04-23T00:07:42.391Z",
  "source": "official-api",
  "officialLatest": {
    "bingo": {
      "game": "bingo",
      "period": "115022749",
      "drawDate": "2026-04-23T08:05:00",
      "redeemableDate": "2026-07-23T00:00:00",
      "numbers": [
        3,
        7,
        12,
        19,
        26,
        30,
        32,
        33,
        35,
        41,
        45,
        47,
        50,
        51,
        65,
        68,
        71,
        72,
        75,
        77
      ],
      "orderNumbers": [
        47,
        71,
        26,
        68,
        72,
        7,
        30,
        19,
        3,
        65,
        75,
        33,
        35,
        50,
        51,
        32,
        45,
        12,
        77,
        41
      ],
      "specialNumber": 41,
      "source": "official-api"
    },
    "daily539": {
      "game": "daily539",
      "period": "115000099",
      "drawDate": "2026-04-22T00:00:00",
      "redeemableDate": "2026-07-22T00:00:00",
      "numbers": [
        5,
        7,
        24,
        38,
        39
      ],
      "source": "official-api"
    },
    "lotto649": {
      "game": "lotto649",
      "period": "115000046",
      "drawDate": "2026-04-21T00:00:00",
      "redeemableDate": "2026-07-21T00:00:00",
      "numbers": [
        1,
        6,
        17,
        19,
        20,
        40
      ],
      "specialNumber": 22,
      "source": "official-api"
    },
    "superLotto638": {
      "game": "superLotto638",
      "period": "115000032",
      "drawDate": "2026-04-20T00:00:00",
      "redeemableDate": "2026-07-20T00:00:00",
      "numbers": [
        7,
        13,
        19,
        34,
        35,
        37
      ],
      "specialNumber": 8,
      "source": "official-api"
    }
  },
  "debugRaw": {
    "bingo": {
      "lotteryBingoLatestPost": {
        "drawTerm": 115022749,
        "dDate": "2026-04-23T08:05:00",
        "eDate": "2026-07-23T00:00:00",
        "bigShowOrder": [
          "03",
          "07",
          "12",
          "19",
          "26",
          "30",
          "32",
          "33",
          "35",
          "41",
          "45",
          "47",
          "50",
          "51",
          "65",
          "68",
          "71",
          "72",
          "75",
          "77"
        ],
        "openShowOrder": [
          "47",
          "71",
          "26",
          "68",
          "72",
          "07",
          "30",
          "19",
          "03",
          "65",
          "75",
          "33",
          "35",
          "50",
          "51",
          "32",
          "45",
          "12",
          "77",
          "41"
        ],
        "prizeNum": {
          "bullEye": "41",
          "highLow": "－",
          "oddEven": "單"
        }
      }
    },
    "bingoWeb": null
  }
}