{
  "generatedAt": "2026-05-14T01:33:13.281Z",
  "source": "official-api",
  "officialLatest": {
    "bingo": {
      "game": "bingo",
      "period": "115027029",
      "drawDate": "2026-05-14T09:30:00",
      "redeemableDate": "2026-08-14T00:00:00",
      "numbers": [
        6,
        12,
        17,
        19,
        23,
        35,
        36,
        37,
        39,
        44,
        45,
        46,
        48,
        52,
        55,
        60,
        62,
        65,
        67,
        69
      ],
      "orderNumbers": [
        60,
        45,
        67,
        48,
        62,
        46,
        12,
        17,
        39,
        44,
        69,
        19,
        23,
        6,
        55,
        35,
        36,
        52,
        65,
        37
      ],
      "specialNumber": 37,
      "source": "official-api"
    },
    "daily539": {
      "game": "daily539",
      "period": "115000117",
      "drawDate": "2026-05-13T00:00:00",
      "redeemableDate": "2026-08-13T00:00:00",
      "numbers": [
        2,
        6,
        7,
        9,
        23
      ],
      "source": "official-api"
    },
    "lotto649": {
      "game": "lotto649",
      "period": "115000052",
      "drawDate": "2026-05-12T00:00:00",
      "redeemableDate": "2026-08-12T00:00:00",
      "numbers": [
        6,
        12,
        18,
        19,
        32,
        36
      ],
      "specialNumber": 34,
      "source": "official-api"
    },
    "superLotto638": {
      "game": "superLotto638",
      "period": "115000038",
      "drawDate": "2026-05-11T00:00:00",
      "redeemableDate": "2026-08-11T00:00:00",
      "numbers": [
        15,
        19,
        23,
        26,
        31,
        38
      ],
      "specialNumber": 5,
      "source": "official-api"
    }
  },
  "debugRaw": {
    "bingo": {
      "lotteryBingoLatestPost": {
        "drawTerm": 115027029,
        "dDate": "2026-05-14T09:30:00",
        "eDate": "2026-08-14T00:00:00",
        "bigShowOrder": [
          "06",
          "12",
          "17",
          "19",
          "23",
          "35",
          "36",
          "37",
          "39",
          "44",
          "45",
          "46",
          "48",
          "52",
          "55",
          "60",
          "62",
          "65",
          "67",
          "69"
        ],
        "openShowOrder": [
          "60",
          "45",
          "67",
          "48",
          "62",
          "46",
          "12",
          "17",
          "39",
          "44",
          "69",
          "19",
          "23",
          "06",
          "55",
          "35",
          "36",
          "52",
          "65",
          "37"
        ],
        "prizeNum": {
          "bullEye": "37",
          "highLow": "－",
          "oddEven": "－"
        }
      }
    },
    "bingoWeb": null
  }
}