{
  "generatedAt": "2026-06-01T00:16:51.032Z",
  "source": "official-api",
  "officialLatest": {
    "bingo": {
      "game": "bingo",
      "period": "115030667",
      "drawDate": "2026-06-01T08:10:00",
      "redeemableDate": "2026-09-01T00:00:00",
      "numbers": [
        3,
        5,
        9,
        11,
        13,
        17,
        19,
        22,
        24,
        27,
        39,
        52,
        53,
        54,
        56,
        57,
        63,
        67,
        75,
        76
      ],
      "orderNumbers": [
        13,
        39,
        11,
        22,
        52,
        53,
        17,
        67,
        27,
        75,
        9,
        76,
        54,
        63,
        19,
        57,
        3,
        5,
        56,
        24
      ],
      "specialNumber": 24,
      "source": "official-api"
    },
    "daily539": {
      "game": "daily539",
      "period": "115000132",
      "drawDate": "2026-05-30T00:00:00",
      "redeemableDate": "2026-08-31T00:00:00",
      "numbers": [
        2,
        3,
        4,
        13,
        39
      ],
      "source": "official-api"
    },
    "lotto649": {
      "game": "lotto649",
      "period": "115000057",
      "drawDate": "2026-05-29T00:00:00",
      "redeemableDate": "2026-08-31T00:00:00",
      "numbers": [
        20,
        26,
        29,
        31,
        37,
        49
      ],
      "specialNumber": 30,
      "source": "official-api"
    },
    "superLotto638": {
      "game": "superLotto638",
      "period": "115000043",
      "drawDate": "2026-05-28T00:00:00",
      "redeemableDate": "2026-08-28T00:00:00",
      "numbers": [
        1,
        2,
        24,
        31,
        34,
        38
      ],
      "specialNumber": 3,
      "source": "official-api"
    }
  },
  "debugRaw": {
    "bingo": {
      "lotteryBingoLatestPost": {
        "drawTerm": 115030667,
        "dDate": "2026-06-01T08:10:00",
        "eDate": "2026-09-01T00:00:00",
        "bigShowOrder": [
          "03",
          "05",
          "09",
          "11",
          "13",
          "17",
          "19",
          "22",
          "24",
          "27",
          "39",
          "52",
          "53",
          "54",
          "56",
          "57",
          "63",
          "67",
          "75",
          "76"
        ],
        "openShowOrder": [
          "13",
          "39",
          "11",
          "22",
          "52",
          "53",
          "17",
          "67",
          "27",
          "75",
          "09",
          "76",
          "54",
          "63",
          "19",
          "57",
          "03",
          "05",
          "56",
          "24"
        ],
        "prizeNum": {
          "bullEye": "24",
          "highLow": "－",
          "oddEven": "單"
        }
      }
    },
    "bingoWeb": null
  }
}